Workbook

Sheet 01 Borrower Overview
A1: Commercial Credit Underwriting Model
A2: Northstar Equipment Services LLC | $750,000 Term Loan
A4: Borrower & Request Summary
A5: Borrower | B5: Northstar Equipment Services LLC
A6: Entity Type | B6: Limited Liability Company (LLC)
A7: Industry | B7: Commercial equipment repair & maintenance
A8: Relationship | B8: New borrower (no prior bank history)
A9: Loan Request | B9: $750,000 senior secured term loan
A10: Purpose | B10: Purchase service vehicles and shop equipment
A11: Repayment Source | B11: Operating cash flow (EBITDA)
A12: Collateral | B12: Service vehicles & equipment (purchase-money lien)
A13: Guarantee | B13: Full personal guarantee of majority owner
A14: Underwriting Question | B14: Should the bank approve this loan?
A16: Proposed Loan Terms (blue = input assumptions)
A17: Term | B17: Value
A18: Loan Amount | B18: 750000
A19: Term (months) | B19: 60
A20: Annual Interest Rate | B20: 0.0825
A21: Amortization | B21: Fully amortizing, monthly P&I
A22: Equity Injection | B22: 85000
A24: How to read this workbook: Blue font = input assumptions you can change. Black font = formulas/outputs driven by the inputs. Each tab flows into the next, ending in the Risk Rating scorecard and Credit Memo recommendation.

Sheet 02 Income Statement
A1: Income Statement
A2: Northstar Equipment Services LLC | USD, fiscal year
A4: Line Item ($) | B4: 2023 | C4: 2024 | D4: 2025
A5: Revenue | B5: 4200000 | C5: 4800000 | D5: 5400000
A6: Cost of Goods Sold (COGS) | B6: 2604000 | C6: 2952000 | D6: 3294000
A7: Gross Profit | B7: =B5-B6 | C7: =C5-C6 | D7: =D5-D6
A8: Operating Expenses (excl. D&A) | B8: 1180000 | C8: 1330000 | D8: 1480000
A9: EBITDA | B9: =B7-B8 | C9: =C7-C8 | D9: =D7-D8
A10: Depreciation & Amortization | B10: 130000 | C10: 145000 | D10: 160000
A11: EBIT (Operating Income) | B11: =B9-B10 | C11: =C9-C10 | D11: =D9-D10
A12: Interest Expense | B12: 95000 | C12: 105000 | D12: 110000
A13: Pre-Tax Income (EBT) | B13: =B11-B12 | C13: =C11-C12 | D13: =D11-D12
A14: Income Taxes | B14: 47750 | C14: 67000 | D14: 89000
A15: Net Income | B15: =B13-B14 | C15: =C13-C14 | D15: =D13-D14
A17: Notes: Gross Profit = Revenue - COGS. EBITDA = Gross Profit - Operating Expenses (a proxy for cash operating earnings before financing, tax and non-cash D&A). Net Income is the bottom-line accrual profit. Revenue grew ~14% (2024) and ~13% (2025) with stable margins - a positive, consistent trend for an underwriter.

Sheet 03 Balance Sheet
A1: Balance Sheet
A2: Northstar Equipment Services LLC | USD, as of year-end
A4: Line Item ($) | B4: 2023 | C4: 2024 | D4: 2025
A5: Assets
A6: Cash & Equivalents | B6: 180000 | C6: 240000 | D6: 320000
A7: Accounts Receivable | B7: 430000 | C7: 490000 | D7: 540000
A8: Inventory | B8: 240000 | C8: 260000 | D8: 280000
A9: Total Current Assets | B9: =SUM(B6:B8) | C9: =SUM(C6:C8) | D9: =SUM(D6:D8)
A10: Net Fixed Assets (PP&E) | B10: 1350000 | C10: 1500000 | D10: 1650000
A11: Total Assets | B11: =B9+B10 | C11: =C9+C10 | D11: =D9+D10
A13: Liabilities & Equity
A14: Accounts Payable | B14: 300000 | C14: 330000 | D14: 360000
A15: Short-Term Debt (incl. CPLTD) | B15: 150000 | C15: 165000 | D15: 180000
A16: Total Current Liabilities | B16: =B14+B15 | C16: =C14+C15 | D16: =D14+D15
A17: Long-Term Debt | B17: 780000 | C17: 820000 | D17: 850000
A18: Total Liabilities | B18: =B16+B17 | C18: =C16+C17 | D18: =D16+D17
A19: Total Equity (members' capital) | B19: 970000 | C19: 1175000 | D19: 1400000
A20: Total Liabilities & Equity | B20: =B18+B19 | C20: =C18+C19 | D20: =D18+D19
A21: Balance Check (TA - TL&E) | B21: =B11-B20 | C21: =C11-C20 | D21: =D11-D20
A23: Notes: Total Equity is an input from the borrower's financials; the Balance Check row confirms Assets = Liabilities + Equity (should be 0). Short-Term Debt includes the current portion of long-term debt (CPLTD).

Sheet 04 Ratio Analysis
A1: Ratio Analysis (Financial Spreading)
A2: Trends, profitability, leverage and liquidity
A4: Ratio | B4: 2023 | C4: 2024 | D4: 2025 | E4: What it means (plain English)
A5: Revenue Growth % | B5: n/a | C5: ='02 Income Statement'!C5/'02 Income Statement'!B5-1 | D5: ='02 Income Statement'!D5/'02 Income Statement'!C5-1 | E5: Year-over-year sales change. Positive, steady growth signals demand and durability.
A6: Gross Margin % | B6: ='02 Income Statement'!B7/'02 Income Statement'!B5 | C6: ='02 Income Statement'!C7/'02 Income Statement'!C5 | D6: ='02 Income Statement'!D7/'02 Income Statement'!D5 | E6: Profit left after direct job costs. Stable margin = good pricing & cost control.
A7: EBITDA Margin % | B7: ='02 Income Statement'!B9/'02 Income Statement'!B5 | C7: ='02 Income Statement'!C9/'02 Income Statement'!C5 | D7: ='02 Income Statement'!D9/'02 Income Statement'!D5 | E7: Cash operating profitability before financing/tax. Drives debt repayment capacity.
A8: Current Ratio | B8: ='03 Balance Sheet'!B9/'03 Balance Sheet'!B16 | C8: ='03 Balance Sheet'!C9/'03 Balance Sheet'!C16 | D8: ='03 Balance Sheet'!D9/'03 Balance Sheet'!D16 | E8: Current assets / current liabilities. >1.5x = comfortable short-term liquidity.
A9: Debt-to-Equity | B9: ='03 Balance Sheet'!B18/'03 Balance Sheet'!B19 | C9: ='03 Balance Sheet'!C18/'03 Balance Sheet'!C19 | D9: ='03 Balance Sheet'!D18/'03 Balance Sheet'!D19 | E9: Total liabilities / equity. Lower = more owner skin-in-the-game, less leverage.
A10: Debt-to-EBITDA | B10: =('03 Balance Sheet'!B15+'03 Balance Sheet'!B17)/'02 Income Statement'!B9 | C10: =('03 Balance Sheet'!C15+'03 Balance Sheet'!C17)/'02 Income Statement'!C9 | D10: =('03 Balance Sheet'!D15+'03 Balance Sheet'!D17)/'02 Income Statement'!D9 | E10: Interest-bearing debt / EBITDA. Years of cash earnings to repay debt; <3.0x is healthy.
A11: Working Capital ($) | B11: ='03 Balance Sheet'!B9-'03 Balance Sheet'!B16 | C11: ='03 Balance Sheet'!C9-'03 Balance Sheet'!C16 | D11: ='03 Balance Sheet'!D9-'03 Balance Sheet'!D16 | E11: Current assets minus current liabilities. Positive cushion funds day-to-day operations.
A13: Underwriter read: Margins are stable, leverage is modest (D/E ~1.0x, Debt/EBITDA <2x) and liquidity is strong (current ratio >2x). The trend is improving across all three years.

Sheet 05 DSCR Analysis
A1: DSCR Analysis (Repayment Capacity)
A2: Cash flow available for debt service vs. debt service
A4: Proposed Loan Debt Service
A5: Item | B5: Value
A6: Loan Amount | B6: ='01 Borrower Overview'!B18
A7: Term (months) | B7: ='01 Borrower Overview'!B19
A8: Annual Interest Rate | B8: ='01 Borrower Overview'!B20
A9: Monthly Payment (P&I) | B9: =PMT('01 Borrower Overview'!B20/12,'01 Borrower Overview'!B19,-'01 Borrower Overview'!B18)
A10: Proposed Annual Debt Service | B10: =B9*12
A11: Existing Annual Debt Service (current loans) | B11: 175000
A12: Total (Global) Annual Debt Service | B12: =B10+B11
A14: Cash Flow Available for Debt Service (CFADS)
A15: Component | B15: 2023 | C15: 2024 | D15: 2025
A16: EBITDA | B16: ='02 Income Statement'!B9 | C16: ='02 Income Statement'!C9 | D16: ='02 Income Statement'!D9
A17: Less: Cash Income Taxes | B17: =-'02 Income Statement'!B14 | C17: =-'02 Income Statement'!C14 | D17: =-'02 Income Statement'!D14
A18: Less: Maintenance Capex (unfinanced) | B18: -55000 | C18: -58000 | D18: -60000
A19: CFADS | B19: =SUM(B16:B18) | C19: =SUM(C16:C18) | D19: =SUM(D16:D18)
A21: Debt Service Coverage Ratio (DSCR)
A22: Metric | B22: 2023 | C22: 2024 | D22: 2025
A23: Proposed-Loan DSCR (CFADS / new DS) | B23: =B19/$B$10 | C23: =C19/$B$10 | D23: =D19/$B$10
A24: Global DSCR (CFADS / total DS) | B24: =B19/$B$12 | C24: =C19/$B$12 | D24: =D19/$B$12
A25: Policy Minimum DSCR | B25: 1.2
A26: Pass / Fail (Global DSCR, 2025) | B26: =IF(D24>=B25,"PASS","FAIL")
A28: DSCR = cash flow available for debt service / debt service. It answers: for every $1 of loan payment, how many dollars of cash does the business generate? Banks typically want >=1.20x. CFADS here = EBITDA - cash taxes - unfinanced maintenance capex (a conservative measure). 2025 global DSCR is comfortably above the 1.20x policy floor even with existing debt.

Sheet 06 Collateral LTV
A1: Collateral & Loan-to-Value (LTV)
A2: Service vehicles & equipment securing the loan
A4: Collateral | B4: Appraised / Cost | C4: Advance Rate | D4: Lendable Value | E4: Basis
A5: Service Vehicles (new, purchase-money) | B5: 520000 | C5: 0.8 | D5: =B5*C5 | E5: Titled rolling stock; NADA values
A6: Shop / Service Equipment (new) | B6: 315000 | C6: 0.7 | D6: =B6*C6 | E6: New machinery; net orderly liquidation
A7: Existing Equipment (additional pledge) | B7: 300000 | C7: 0.6 | D7: =B7*C7 | E7: Used; discounted forced-sale value
A8: Total Collateral Value | B8: =SUM(B5:B7) | D8: =SUM(D5:D7)
A10: LTV & Collateral Coverage
A11: Metric | B11: Value
A12: Loan Amount | B12: ='01 Borrower Overview'!B18
A13: LTV vs. Appraised Value | B13: ='01 Borrower Overview'!B18/B8
A14: LTV vs. Lendable (discounted) Value | B14: ='01 Borrower Overview'!B18/D8
A15: Collateral Coverage (lendable / loan) | B15: =D8/'01 Borrower Overview'!B18
A16: Policy Min. Coverage | B16: 1
A17: Pass / Fail | B17: =IF(B15>=B16,"PASS","FAIL")
A19: Advance rate = the % of value a lender will lend against after a liquidation haircut (vehicles hold value better than used equipment). LTV = loan / collateral value; lower is safer. Collateral coverage >=1.0x on lendable value means the bank can expect to recover the loan in a default. Coverage here is adequate but not abundant - secondary, not primary, repayment.

Sheet 07 Risk Rating
A1: Risk Rating Scorecard
A2: Weighted 1 (strong) - 5 (weak); lower is better
A4: Risk Factor | B4: Weight | C4: Score 1-5 | D4: Weighted | E4: Rationale
A5: Repayment Capacity (DSCR) | B5: 0.25 | C5: 2 | D5: =B5*C5 | E5: Global DSCR ~1.3x, proposed-loan DSCR >2.5x; healthy cushion.
A6: Leverage | B6: 0.15 | C6: 3 | D6: =B6*C6 | E6: D/E ~1.0x and Debt/EBITDA <2x - moderate, in line with industry.
A7: Liquidity | B7: 0.1 | C7: 2 | D7: =B7*C7 | E7: Current ratio >2x; positive and growing working capital.
A8: Collateral Coverage | B8: 0.15 | C8: 3 | D8: =B8*C8 | E8: ~1.05x lendable coverage; adequate but not strong; depreciating assets.
A9: Management | B9: 0.1 | C9: 3 | D9: =B9*C9 | E9: Experienced operator but new, unseasoned banking relationship.
A10: Industry Risk | B10: 0.1 | C10: 3 | D10: =B10*C10 | E10: Equipment repair is cyclical/competitive but demand is non-discretionary.
A11: Financial Trends | B11: 0.15 | C11: 2 | D11: =B11*C11 | E11: Three years of revenue growth with stable margins and rising equity.
A12: Weighted Composite Score | B12: =SUM(B5:B11) | D12: =SUM(D5:D11)
A13: Risk Grade (1-7 scale) | D13: =IF(D12<=1.5,"2 - Strong",IF(D12<=2.5,"4 - Satisfactory",IF(D12<=3.5,"5 - Acceptable / Watch",IF(D12<=4.2,"6 - Special Mention","7 - Substandard"))))
A15: Each factor is scored 1 (strong) to 5 (weak) and multiplied by its weight; the weighted scores sum to a composite that maps to an internal risk grade. A composite around 2.5 lands in the low end of 'Acceptable' - a pass grade that typically supports approval with conditions.

Sheet 08 Credit Memo
A1: Credit Memo & Recommendation
A2: Northstar Equipment Services LLC | $750,000 Term Loan
A4: Recommendation
A5: Decision | B5: APPROVE WITH CONDITIONS
A6: Risk Grade | B6: ='07 Risk Rating'!D13
A7: 2025 Global DSCR | B7: ='05 DSCR Analysis'!D24
A8: Collateral Coverage | B8: ='06 Collateral LTV'!B15
A10: Summary
B11: • Northstar Equipment Services LLC requests a $750,000, 60-month term loan at 8.25% to purchase service vehicles and shop equipment, with a $85,000 owner equity injection.
B12: • The company shows three years of steady revenue growth (~$4.2M to $5.4M), stable ~39% gross margins, modest leverage, and strong liquidity. Cash flow comfortably covers the new debt.
A14: Strengths
B15: • Consistent revenue growth and stable margins across 2023-2025.
B16: • Strong repayment capacity: proposed-loan DSCR >2.5x and global DSCR ~1.3x, above the 1.20x floor.
B17: • Modest leverage (Debt/EBITDA <2x, D/E ~1.0x) and healthy liquidity (current ratio >2x).
B18: • Loan is purchase-money secured by titled vehicles and equipment, plus a personal guarantee.
B19: • Owner contributes equity (skin in the game), reducing effective LTV.
A21: Weaknesses
B22: • New banking relationship with no prior repayment history at this institution.
B23: • Collateral is depreciating; lendable coverage (~1.05x) is adequate but not abundant.
B24: • Single-owner dependency (key-person risk); LLC financials likely company-prepared/reviewed.
A26: Key Risks
B27: • Cyclicality: a downturn in customers' capital spending could compress repair volumes/revenue.
B28: • Asset depreciation could outpace loan amortization, weakening collateral coverage over time.
B29: • Margin/customer concentration risk not fully visible from summary financials.
A31: Mitigants
B32: • Conservative DSCR (after maintenance capex) leaves cushion against a revenue decline.
B33: • Purchase-money lien on financed assets + additional equipment pledge and personal guarantee.
B34: • Non-discretionary nature of equipment repair supports demand resilience through cycles.
B35: • Equity injection and amortizing structure de-risk the bank's exposure over the term.
A37: Approval Conditions
B38: • First-priority (purchase-money) lien on all financed vehicles and equipment; UCC-1 filed.
B39: • Unlimited personal guarantee of the majority owner.
B40: • Minimum equity injection of $85,000 verified at closing.
B41: • Financial covenants: maintain global DSCR >=1.20x and Debt/EBITDA <=3.5x, tested annually.
B42: • Annual CPA-reviewed financial statements and interim statements upon request.
B43: • Proof of insurance on collateral with bank named as loss payee.
A45: This memo is the underwriter's written recommendation. The decision, risk grade and key metrics above pull live from the model tabs, so changing an assumption updates the memo.

Sheet 09 Sensitivity Analysis
A1: Sensitivity / Downside Scenario Analysis
A2: How does the credit hold up if performance weakens?
A4: Scenario Stress Drivers (blue = inputs)
A5: Assumption | B5: Base Case | C5: Downside | D5: Stress | E5: Comment
A6: Revenue Decline vs. 2025 | B6: 0 | C6: 0.07 | D6: 0.15 | E6: Lower repair volumes / lost customers
A7: EBITDA Margin Compression (pts) | B7: 0 | C7: 0.01 | D7: 0.03 | E7: Pricing pressure, wage/parts inflation
A8: Additional Operating Expenses ($) | B8: 0 | C8: 20000 | D8: 50000 | E8: Fuel, insurance, repairs above plan
A10: Shared Model Inputs (pulled live from other tabs)
A11: Input | B11: Value
A12: 2025 Base Revenue | B12: ='02 Income Statement'!D5
A13: 2025 Base EBITDA Margin | B13: ='02 Income Statement'!D9/'02 Income Statement'!D5
A14: Depreciation & Amortization | B14: ='02 Income Statement'!D10
A15: Interest Expense | B15: ='02 Income Statement'!D12
A16: Effective Tax Rate | B16: 0.25
A17: Maintenance Capex (unfinanced) | B17: 60000
A18: Total Annual Debt Service | B18: ='05 DSCR Analysis'!B12
A19: DSCR Covenant Minimum | B19: ='05 DSCR Analysis'!B25
A21: Scenario Results (recalculated CFADS & DSCR)
A22: Metric | B22: Base Case | C22: Downside | D22: Stress
A23: Stressed Revenue | B23: =$B$12*(1-B6) | C23: =$B$12*(1-C6) | D23: =$B$12*(1-D6)
A24: Stressed EBITDA Margin | B24: =$B$13-B7 | C24: =$B$13-C7 | D24: =$B$13-D7
A25: EBITDA before extra OpEx | B25: =B23*B24 | C25: =C23*C24 | D25: =D23*D24
A26: Less: Additional OpEx | B26: =-B8 | C26: =-C8 | D26: =-D8
A27: Stressed EBITDA | B27: =B25+B26 | C27: =C25+C26 | D27: =D25+D26
A28: Less: Cash Taxes | B28: =-MAX(0,$B$16*(B27-$B$14-$B$15)) | C28: =-MAX(0,$B$16*(C27-$B$14-$B$15)) | D28: =-MAX(0,$B$16*(D27-$B$14-$B$15))
A29: Less: Maintenance Capex | B29: =-$B$17 | C29: =-$B$17 | D29: =-$B$17
A30: CFADS (stressed) | B30: =B27+B28+B29 | C30: =C27+C28+C29 | D30: =D27+D28+D29
A31: Global DSCR | B31: =B30/$B$18 | C31: =C30/$B$18 | D31: =D30/$B$18
A33: Pass / Fail Tests
A34: Test | B34: Base Case | C34: Downside | D34: Stress | E34: Meaning
A35: DSCR Covenant Test (>= 1.20x) | B35: =IF(B31>=$B$19,"PASS","FAIL") | C35: =IF(C31>=$B$19,"PASS","FAIL") | D35: =IF(D31>=$B$19,"PASS","FAIL") | E35: Meets the loan's DSCR covenant
A36: Cash Coverage Test (>= 1.00x) | B36: =IF(B31>=1,"PASS","FAIL") | C36: =IF(C31>=1,"PASS","FAIL") | D36: =IF(D31>=1,"PASS","FAIL") | E36: Cash flow still fully covers debt service
A38: Why this matters: Underwriters never lend on the base case alone. Sensitivity (downside) analysis stresses the borrower's revenue and margins to find the breaking point and confirm the loan still services - or to size the cushion if it does not. Here the Base Case clears the 1.20x covenant; a moderate Downside breaches the covenant but cash flow still covers debt service (DSCR > 1.0x); the severe Stress case fails both - the credit would then rely on collateral and the personal guarantee. This is exactly why the deal is 'Approve WITH conditions' (DSCR covenant, equity injection, collateral, guarantee) rather than an unconditional approval.
